mpneuralnetwork/__init__.py
mpneuralnetwork/activations.py
mpneuralnetwork/backend.py
mpneuralnetwork/losses.py
mpneuralnetwork/metrics.py
mpneuralnetwork/model.py
mpneuralnetwork/optimizers.py
mpneuralnetwork/serialization.py
mpneuralnetwork/layers/__init__.py
mpneuralnetwork/layers/layer.py
mpneuralnetwork/layers/layer1d.py
mpneuralnetwork/layers/layer2d.py
mpneuralnetwork/layers/utils.py
mpneuralnetwork-1.1.1.dist-info/METADATA
mpneuralnetwork-1.1.1.dist-info/WHEEL
mpneuralnetwork-1.1.1.dist-info/licenses/LICENSE
mpneuralnetwork-1.1.1.dist-info/RECORD
