Metadata-Version: 2.4
Name: mpneuralnetwork
Version: 1.1.1
Summary: A fully vectorized Deep Learning framework built from scratch using only NumPy.
Project-URL: Homepage, https://pypi.org/project/mpneuralnetwork/
Project-URL: Repository, https://github.com/maximepires4/mp-neural-network
Project-URL: Issues, https://github.com/maximepires4/mp-neural-network/issues
Project-URL: Documentation, https://maximepires4.github.io/mp-neural-network/
Author-email: Maxime Pires <maximepires4@gmail.com>
License: Copyright (c) 2018 The Python Packaging Authority
License-File: LICENSE
Keywords: ai,deep-learning,education,machine-learning,neural-network,numpy
Classifier: Development Status :: 5 - Production/Stable
Classifier: Intended Audience :: Developers
Classifier: Intended Audience :: Education
Classifier: Intended Audience :: Science/Research
Classifier: License :: OSI Approved :: MIT License
Classifier: Operating System :: OS Independent
Classifier: Programming Language :: Python :: 3
Classifier: Programming Language :: Python :: 3.10
Classifier: Programming Language :: Python :: 3.11
Classifier: Programming Language :: Python :: 3.12
Classifier: Topic :: Scientific/Engineering :: Artificial Intelligence
Classifier: Topic :: Scientific/Engineering :: Mathematics
Requires-Python: >=3.10
Requires-Dist: numpy>=1.21
Provides-Extra: build
Requires-Dist: build; extra == 'build'
Requires-Dist: python-semantic-release; extra == 'build'
Requires-Dist: twine; extra == 'build'
Provides-Extra: dev
Requires-Dist: mypy>=1.9.0; extra == 'dev'
Requires-Dist: pre-commit>=3.5.0; extra == 'dev'
Requires-Dist: ruff==0.14.5; extra == 'dev'
Requires-Dist: types-setuptools; extra == 'dev'
Provides-Extra: docs
Requires-Dist: mkdocs-material; extra == 'docs'
Requires-Dist: mkdocstrings[python]; extra == 'docs'
Provides-Extra: example
Requires-Dist: pandas>=1.5.0; extra == 'example'
Provides-Extra: profile
Requires-Dist: memray; extra == 'profile'
Requires-Dist: snakeviz; extra == 'profile'
Provides-Extra: test
Requires-Dist: pytest-cov>=4.0; extra == 'test'
Requires-Dist: pytest>=7.0; extra == 'test'
